kalirootcli/__init__.py
kalirootcli/__main__.py
kalirootcli/agent.py
kalirootcli/ai_handler.py
kalirootcli/api_client.py
kalirootcli/audio.py
kalirootcli/auth.py
kalirootcli/autonomous.py
kalirootcli/chat_manager.py
kalirootcli/cli_wrapper.py
kalirootcli/config.py
kalirootcli/database_manager.py
kalirootcli/distro_detector.py
kalirootcli/main.py
kalirootcli/payments.py
kalirootcli/project_manager.py
kalirootcli/rag_engine.py
kalirootcli/reporting.py
kalirootcli/security.py
kalirootcli/subscription.py
kalirootcli/system_collector.py
kalirootcli/web_search.py
kalirootcli/mobile/__init__.py
kalirootcli/mobile/android_api.py
kalirootcli/mobile/haptics.py
kalirootcli/tools/__init__.py
kalirootcli/tools/cve_lookup.py
kalirootcli/tools/extra.py
kalirootcli/tools/fsociety_handler.py
kalirootcli/tools/platform_utils.py
kalirootcli/tools/port_scanner.py
kalirootcli/tools/repo_browser.py
kalirootcli/tools/repos_data.py
kalirootcli/tools/script_generator.py
kalirootcli/ui/__init__.py
kalirootcli/ui/colors.py
kalirootcli/ui/display.py
kalirootcli/ui/menus.py
kalirootcli/ui/splash.py
kr_cli_dominion-6.0.1.dist-info/licenses/LICENSE
kr_cli_dominion-6.0.1.dist-info/METADATA
kr_cli_dominion-6.0.1.dist-info/WHEEL
kr_cli_dominion-6.0.1.dist-info/entry_points.txt
kr_cli_dominion-6.0.1.dist-info/top_level.txt
kr_cli_dominion-6.0.1.dist-info/RECORD
