Metadata-Version: 2.4
Name: kr-cli-dominion
Version: 6.0.1
Summary: Advanced AI-Powered Security CLI - DOMINION Model with Educational Platform
Author-email: KaliRootCode <kalirootcode@proton.me>
License: MIT
Project-URL: Homepage, https://github.com/kalirootcode/KaliRootCLI
Project-URL: Repository, https://github.com/kalirootcode/KaliRootCLI
Project-URL: Issues, https://github.com/kalirootcode/KaliRootCLI/issues
Keywords: cybersecurity,hacking,pentesting,kali,termux,cli,ai,agent
Classifier: Development Status :: 5 - Production/Stable
Classifier: Environment :: Console
Classifier: Intended Audience :: Developers
Classifier: Intended Audience :: Information Technology
Classifier: License :: OSI Approved :: MIT License
Classifier: Operating System :: POSIX :: Linux
Classifier: Operating System :: Android
Classifier: Programming Language :: Python :: 3
Classifier: Programming Language :: Python :: 3.8
Classifier: Programming Language :: Python :: 3.9
Classifier: Programming Language :: Python :: 3.10
Classifier: Programming Language :: Python :: 3.11
Classifier: Programming Language :: Python :: 3.12
Classifier: Topic :: Security
Classifier: Topic :: System :: Systems Administration
Requires-Python: >=3.8
License-File: LICENSE
Requires-Dist: requests>=2.31.0
Requires-Dist: rich>=13.0.0
Requires-Dist: python-dotenv>=1.0.0
Requires-Dist: tiktoken>=0.5.0
Requires-Dist: groq>=0.4.0
Requires-Dist: supabase>=2.0.0
Requires-Dist: reportlab>=4.0.0
Requires-Dist: beautifulsoup4>=4.12.0
Provides-Extra: websearch
Requires-Dist: duckduckgo-search>=6.0.0; extra == "websearch"
Provides-Extra: audio
Requires-Dist: sounddevice>=0.4.6; extra == "audio"
Requires-Dist: scipy>=1.11.0; extra == "audio"
Requires-Dist: numpy>=1.26.0; extra == "audio"
Provides-Extra: full
Requires-Dist: duckduckgo-search>=6.0.0; extra == "full"
Requires-Dist: sounddevice>=0.4.6; extra == "full"
Requires-Dist: scipy>=1.11.0; extra == "full"
Requires-Dist: numpy>=1.26.0; extra == "full"
Dynamic: license-file
